README.rst
setup.py
unread_decorator.py
unread_decorator.egg-info/PKG-INFO
unread_decorator.egg-info/SOURCES.txt
unread_decorator.egg-info/dependency_links.txt
unread_decorator.egg-info/top_level.txt