Metadata-Version: 1.1
Name: unread-decorator
Version: 1.0
Summary: unread() for streams, unnext() for iterators
Home-page: http://github.com/prechelt/unread-decorator
Author: Lutz Prechelt
Author-email: prechelt@inf.fu-berlin.de
License: BSD License
Keywords: undo,I/O,iterator
Platform: UNKNOWN
Classifier: License :: OSI Approved :: BSD License
Classifier: Development Status :: 4 - Beta
Classifier: Intended Audience :: Developers
Classifier: Topic :: Software Development :: Libraries :: Python Modules
Classifier: Programming Language :: Python :: 3
Classifier: Programming Language :: Python :: 3.3
Classifier: Programming Language :: Python :: 3.4
